kse_memory/__init__.py
kse_memory/cli.py
kse_memory/exceptions.py
kse_memory/adapters/__init__.py
kse_memory/adapters/generic.py
kse_memory/adapters/shopify.py
kse_memory/adapters/woocommerce.py
kse_memory/backends/__init__.py
kse_memory/backends/arangodb.py
kse_memory/backends/chromadb.py
kse_memory/backends/milvus.py
kse_memory/backends/mock.py
kse_memory/backends/mongodb.py
kse_memory/backends/neo4j.py
kse_memory/backends/pinecone.py
kse_memory/backends/postgresql.py
kse_memory/backends/qdrant.py
kse_memory/backends/weaviate.py
kse_memory/core/__init__.py
kse_memory/core/config.py
kse_memory/core/domain_mapping.py
kse_memory/core/interfaces.py
kse_memory/core/memory.py
kse_memory/core/models.py
kse_memory/core/production_validator.py
kse_memory/federated/__init__.py
kse_memory/federated/federated_client.py
kse_memory/federated/federated_coordinator.py
kse_memory/federated/federated_models.py
kse_memory/federated/privacy.py
kse_memory/integrations/__init__.py
kse_memory/integrations/langchain.py
kse_memory/integrations/llamaindex.py
kse_memory/quickstart/__init__.py
kse_memory/quickstart/backend_detector.py
kse_memory/quickstart/benchmark.py
kse_memory/quickstart/datasets.py
kse_memory/quickstart/demo.py
kse_memory/services/__init__.py
kse_memory/services/cache.py
kse_memory/services/conceptual.py
kse_memory/services/embedding.py
kse_memory/services/search.py
kse_memory/temporal/__init__.py
kse_memory/temporal/temporal_conceptual.py
kse_memory/temporal/temporal_graph.py
kse_memory/temporal/temporal_kse.py
kse_memory/temporal/temporal_models.py
kse_memory/temporal/time_embeddings.py
kse_memory/visual/__init__.py
kse_memory/visual/conceptual_explorer.py
kse_memory/visual/dashboard.py
kse_memory/visual/graph_visualizer.py
kse_memory/visual/search_explainer.py
kse_memory_sdk-2.0.0.dist-info/METADATA
kse_memory_sdk-2.0.0.dist-info/WHEEL
kse_memory_sdk-2.0.0.dist-info/entry_points.txt
kse_memory_sdk-2.0.0.dist-info/licenses/LICENSE
kse_memory_sdk-2.0.0.dist-info/RECORD
