Metadata-Version: 2.4
Name: kse-memory-sdk
Version: 2.0.0
Summary: Industry-Agnostic Hybrid Knowledge Retrieval for Intelligent Applications
Project-URL: Homepage, https://github.com/kse-memory/kse-memory-sdk
Project-URL: Documentation, https://kse-memory-sdk.readthedocs.io
Project-URL: Repository, https://github.com/kse-memory/kse-memory-sdk
Project-URL: Bug Tracker, https://github.com/kse-memory/kse-memory-sdk/issues
Project-URL: Changelog, https://github.com/kse-memory/kse-memory-sdk/blob/main/CHANGELOG.md
Author-email: KSE Memory Team <team@kse-memory.com>
License-Expression: MIT
License-File: LICENSE
Keywords: ai,conceptual-spaces,embeddings,enterprise,finance,healthcare,hybrid-ai,knowledge-graph,rag,real-estate,research,retail,retrieval,search,universal-data-model
Classifier: Development Status :: 5 - Production/Stable
Classifier: Intended Audience :: Developers
Classifier: License :: OSI Approved :: MIT License
Classifier: Programming Language :: Python :: 3
Classifier: Programming Language :: Python :: 3.8
Classifier: Programming Language :: Python :: 3.9
Classifier: Programming Language :: Python :: 3.10
Classifier: Programming Language :: Python :: 3.11
Classifier: Programming Language :: Python :: 3.12
Classifier: Topic :: Scientific/Engineering :: Artificial Intelligence
Classifier: Topic :: Software Development :: Libraries :: Python Modules
Classifier: Topic :: Text Processing :: Indexing
Requires-Python: >=3.8
Requires-Dist: aiofiles>=23.0.0
Requires-Dist: asyncio-mqtt>=0.11.0
Requires-Dist: click>=8.0.0
Requires-Dist: httpx>=0.24.0
Requires-Dist: networkx>=3.0.0
Requires-Dist: numpy>=1.21.0
Requires-Dist: psycopg2-binary>=2.9.0
Requires-Dist: pydantic>=2.0.0
Requires-Dist: pyyaml>=6.0.0
Requires-Dist: redis>=4.5.0
Requires-Dist: rich>=13.0.0
Requires-Dist: scikit-learn>=1.3.0
Requires-Dist: sentence-transformers>=2.2.0
Provides-Extra: all
Requires-Dist: chromadb>=0.4.0; extra == 'all'
Requires-Dist: fastapi>=0.104.0; extra == 'all'
Requires-Dist: jinja2>=3.1.0; extra == 'all'
Requires-Dist: langchain-core>=0.1.0; extra == 'all'
Requires-Dist: langchain>=0.1.0; extra == 'all'
Requires-Dist: llama-index-core>=0.9.0; extra == 'all'
Requires-Dist: llama-index>=0.9.0; extra == 'all'
Requires-Dist: motor>=3.3.0; extra == 'all'
Requires-Dist: neo4j>=5.0.0; extra == 'all'
Requires-Dist: pinecone-client>=3.0.0; extra == 'all'
Requires-Dist: pymilvus>=2.3.0; extra == 'all'
Requires-Dist: python-arango>=7.5.0; extra == 'all'
Requires-Dist: qdrant-client>=1.6.0; extra == 'all'
Requires-Dist: shopifyapi>=12.0.0; extra == 'all'
Requires-Dist: uvicorn>=0.24.0; extra == 'all'
Requires-Dist: weaviate-client>=3.25.0; extra == 'all'
Requires-Dist: websockets>=11.0.0; extra == 'all'
Requires-Dist: woocommerce>=3.0.0; extra == 'all'
Provides-Extra: arangodb
Requires-Dist: python-arango>=7.5.0; extra == 'arangodb'
Provides-Extra: chroma
Requires-Dist: chromadb>=0.4.0; extra == 'chroma'
Provides-Extra: dev
Requires-Dist: black>=23.0.0; extra == 'dev'
Requires-Dist: flake8>=6.0.0; extra == 'dev'
Requires-Dist: hypothesis>=6.0.0; extra == 'dev'
Requires-Dist: matplotlib>=3.5.0; extra == 'dev'
Requires-Dist: mypy>=1.5.0; extra == 'dev'
Requires-Dist: pre-commit>=3.0.0; extra == 'dev'
Requires-Dist: pytest-asyncio>=0.21.0; extra == 'dev'
Requires-Dist: pytest-cov>=4.0.0; extra == 'dev'
Requires-Dist: pytest>=7.0.0; extra == 'dev'
Requires-Dist: seaborn>=0.11.0; extra == 'dev'
Requires-Dist: sphinx-rtd-theme>=1.3.0; extra == 'dev'
Requires-Dist: sphinx>=7.0.0; extra == 'dev'
Requires-Dist: torch>=2.0.0; extra == 'dev'
Provides-Extra: langchain
Requires-Dist: langchain-core>=0.1.0; extra == 'langchain'
Requires-Dist: langchain>=0.1.0; extra == 'langchain'
Provides-Extra: llamaindex
Requires-Dist: llama-index-core>=0.9.0; extra == 'llamaindex'
Requires-Dist: llama-index>=0.9.0; extra == 'llamaindex'
Provides-Extra: milvus
Requires-Dist: pymilvus>=2.3.0; extra == 'milvus'
Provides-Extra: mongodb
Requires-Dist: motor>=3.3.0; extra == 'mongodb'
Provides-Extra: neo4j
Requires-Dist: neo4j>=5.0.0; extra == 'neo4j'
Provides-Extra: pinecone
Requires-Dist: pinecone-client>=3.0.0; extra == 'pinecone'
Provides-Extra: qdrant
Requires-Dist: qdrant-client>=1.6.0; extra == 'qdrant'
Provides-Extra: shopify
Requires-Dist: shopifyapi>=12.0.0; extra == 'shopify'
Provides-Extra: visual
Requires-Dist: fastapi>=0.104.0; extra == 'visual'
Requires-Dist: jinja2>=3.1.0; extra == 'visual'
Requires-Dist: uvicorn>=0.24.0; extra == 'visual'
Requires-Dist: websockets>=11.0.0; extra == 'visual'
Provides-Extra: weaviate
Requires-Dist: weaviate-client>=3.25.0; extra == 'weaviate'
Provides-Extra: woocommerce
Requires-Dist: woocommerce>=3.0.0; extra == 'woocommerce'
